LICENSE
MANIFEST.in
README.md
check_code
pylintrc
requirements.txt
setup.py
test-requirements.txt
concoursepy/__init__.py
concoursepy/api.py
ol_concoursepy.egg-info/PKG-INFO
ol_concoursepy.egg-info/SOURCES.txt
ol_concoursepy.egg-info/dependency_links.txt
ol_concoursepy.egg-info/requires.txt
ol_concoursepy.egg-info/top_level.txt