Metadata-Version: 2.1
Name: ol-concoursepy
Version: 0.0.41
Summary: library to interface with concourse
Home-page: https://github.com/arwineap/concoursepy
Author: Alex Arwine
Author-email: arwineap@gmail.com
Classifier: Programming Language :: Python :: 3
Classifier: License :: OSI Approved :: MIT License
Classifier: Operating System :: OS Independent
License-File: LICENSE
